{
  "meta": {
    "area": "SE3",
    "documentType": "A44",
    "timeZone": "Europe/Stockholm",
    "date": "2026-02-03",
    "resolutionMinutes": 15,
    "expected": 96,
    "present": 96,
    "updatedAt": "2026-02-03T12:30:09.324Z",
    "historyUpdatedAt": "2026-02-03T12:30:09.304Z",
    "eursek": 10.5935,
    "eursekDate": "2026-02-02",
    "includesTransferFee": false
  },
  "timeline": [
    {
      "utc": "2026-02-02T23:00:00.000Z",
      "time": "00:00"
    },
    {
      "utc": "2026-02-02T23:15:00.000Z",
      "time": "00:15"
    },
    {
      "utc": "2026-02-02T23:30:00.000Z",
      "time": "00:30"
    },
    {
      "utc": "2026-02-02T23:45:00.000Z",
      "time": "00:45"
    },
    {
      "utc": "2026-02-03T00:00:00.000Z",
      "time": "01:00"
    },
    {
      "utc": "2026-02-03T00:15:00.000Z",
      "time": "01:15"
    },
    {
      "utc": "2026-02-03T00:30:00.000Z",
      "time": "01:30"
    },
    {
      "utc": "2026-02-03T00:45:00.000Z",
      "time": "01:45"
    },
    {
      "utc": "2026-02-03T01:00:00.000Z",
      "time": "02:00"
    },
    {
      "utc": "2026-02-03T01:15:00.000Z",
      "time": "02:15"
    },
    {
      "utc": "2026-02-03T01:30:00.000Z",
      "time": "02:30"
    },
    {
      "utc": "2026-02-03T01:45:00.000Z",
      "time": "02:45"
    },
    {
      "utc": "2026-02-03T02:00:00.000Z",
      "time": "03:00"
    },
    {
      "utc": "2026-02-03T02:15:00.000Z",
      "time": "03:15"
    },
    {
      "utc": "2026-02-03T02:30:00.000Z",
      "time": "03:30"
    },
    {
      "utc": "2026-02-03T02:45:00.000Z",
      "time": "03:45"
    },
    {
      "utc": "2026-02-03T03:00:00.000Z",
      "time": "04:00"
    },
    {
      "utc": "2026-02-03T03:15:00.000Z",
      "time": "04:15"
    },
    {
      "utc": "2026-02-03T03:30:00.000Z",
      "time": "04:30"
    },
    {
      "utc": "2026-02-03T03:45:00.000Z",
      "time": "04:45"
    },
    {
      "utc": "2026-02-03T04:00:00.000Z",
      "time": "05:00"
    },
    {
      "utc": "2026-02-03T04:15:00.000Z",
      "time": "05:15"
    },
    {
      "utc": "2026-02-03T04:30:00.000Z",
      "time": "05:30"
    },
    {
      "utc": "2026-02-03T04:45:00.000Z",
      "time": "05:45"
    },
    {
      "utc": "2026-02-03T05:00:00.000Z",
      "time": "06:00"
    },
    {
      "utc": "2026-02-03T05:15:00.000Z",
      "time": "06:15"
    },
    {
      "utc": "2026-02-03T05:30:00.000Z",
      "time": "06:30"
    },
    {
      "utc": "2026-02-03T05:45:00.000Z",
      "time": "06:45"
    },
    {
      "utc": "2026-02-03T06:00:00.000Z",
      "time": "07:00"
    },
    {
      "utc": "2026-02-03T06:15:00.000Z",
      "time": "07:15"
    },
    {
      "utc": "2026-02-03T06:30:00.000Z",
      "time": "07:30"
    },
    {
      "utc": "2026-02-03T06:45:00.000Z",
      "time": "07:45"
    },
    {
      "utc": "2026-02-03T07:00:00.000Z",
      "time": "08:00"
    },
    {
      "utc": "2026-02-03T07:15:00.000Z",
      "time": "08:15"
    },
    {
      "utc": "2026-02-03T07:30:00.000Z",
      "time": "08:30"
    },
    {
      "utc": "2026-02-03T07:45:00.000Z",
      "time": "08:45"
    },
    {
      "utc": "2026-02-03T08:00:00.000Z",
      "time": "09:00"
    },
    {
      "utc": "2026-02-03T08:15:00.000Z",
      "time": "09:15"
    },
    {
      "utc": "2026-02-03T08:30:00.000Z",
      "time": "09:30"
    },
    {
      "utc": "2026-02-03T08:45:00.000Z",
      "time": "09:45"
    },
    {
      "utc": "2026-02-03T09:00:00.000Z",
      "time": "10:00"
    },
    {
      "utc": "2026-02-03T09:15:00.000Z",
      "time": "10:15"
    },
    {
      "utc": "2026-02-03T09:30:00.000Z",
      "time": "10:30"
    },
    {
      "utc": "2026-02-03T09:45:00.000Z",
      "time": "10:45"
    },
    {
      "utc": "2026-02-03T10:00:00.000Z",
      "time": "11:00"
    },
    {
      "utc": "2026-02-03T10:15:00.000Z",
      "time": "11:15"
    },
    {
      "utc": "2026-02-03T10:30:00.000Z",
      "time": "11:30"
    },
    {
      "utc": "2026-02-03T10:45:00.000Z",
      "time": "11:45"
    },
    {
      "utc": "2026-02-03T11:00:00.000Z",
      "time": "12:00"
    },
    {
      "utc": "2026-02-03T11:15:00.000Z",
      "time": "12:15"
    },
    {
      "utc": "2026-02-03T11:30:00.000Z",
      "time": "12:30"
    },
    {
      "utc": "2026-02-03T11:45:00.000Z",
      "time": "12:45"
    },
    {
      "utc": "2026-02-03T12:00:00.000Z",
      "time": "13:00"
    },
    {
      "utc": "2026-02-03T12:15:00.000Z",
      "time": "13:15"
    },
    {
      "utc": "2026-02-03T12:30:00.000Z",
      "time": "13:30"
    },
    {
      "utc": "2026-02-03T12:45:00.000Z",
      "time": "13:45"
    },
    {
      "utc": "2026-02-03T13:00:00.000Z",
      "time": "14:00"
    },
    {
      "utc": "2026-02-03T13:15:00.000Z",
      "time": "14:15"
    },
    {
      "utc": "2026-02-03T13:30:00.000Z",
      "time": "14:30"
    },
    {
      "utc": "2026-02-03T13:45:00.000Z",
      "time": "14:45"
    },
    {
      "utc": "2026-02-03T14:00:00.000Z",
      "time": "15:00"
    },
    {
      "utc": "2026-02-03T14:15:00.000Z",
      "time": "15:15"
    },
    {
      "utc": "2026-02-03T14:30:00.000Z",
      "time": "15:30"
    },
    {
      "utc": "2026-02-03T14:45:00.000Z",
      "time": "15:45"
    },
    {
      "utc": "2026-02-03T15:00:00.000Z",
      "time": "16:00"
    },
    {
      "utc": "2026-02-03T15:15:00.000Z",
      "time": "16:15"
    },
    {
      "utc": "2026-02-03T15:30:00.000Z",
      "time": "16:30"
    },
    {
      "utc": "2026-02-03T15:45:00.000Z",
      "time": "16:45"
    },
    {
      "utc": "2026-02-03T16:00:00.000Z",
      "time": "17:00"
    },
    {
      "utc": "2026-02-03T16:15:00.000Z",
      "time": "17:15"
    },
    {
      "utc": "2026-02-03T16:30:00.000Z",
      "time": "17:30"
    },
    {
      "utc": "2026-02-03T16:45:00.000Z",
      "time": "17:45"
    },
    {
      "utc": "2026-02-03T17:00:00.000Z",
      "time": "18:00"
    },
    {
      "utc": "2026-02-03T17:15:00.000Z",
      "time": "18:15"
    },
    {
      "utc": "2026-02-03T17:30:00.000Z",
      "time": "18:30"
    },
    {
      "utc": "2026-02-03T17:45:00.000Z",
      "time": "18:45"
    },
    {
      "utc": "2026-02-03T18:00:00.000Z",
      "time": "19:00"
    },
    {
      "utc": "2026-02-03T18:15:00.000Z",
      "time": "19:15"
    },
    {
      "utc": "2026-02-03T18:30:00.000Z",
      "time": "19:30"
    },
    {
      "utc": "2026-02-03T18:45:00.000Z",
      "time": "19:45"
    },
    {
      "utc": "2026-02-03T19:00:00.000Z",
      "time": "20:00"
    },
    {
      "utc": "2026-02-03T19:15:00.000Z",
      "time": "20:15"
    },
    {
      "utc": "2026-02-03T19:30:00.000Z",
      "time": "20:30"
    },
    {
      "utc": "2026-02-03T19:45:00.000Z",
      "time": "20:45"
    },
    {
      "utc": "2026-02-03T20:00:00.000Z",
      "time": "21:00"
    },
    {
      "utc": "2026-02-03T20:15:00.000Z",
      "time": "21:15"
    },
    {
      "utc": "2026-02-03T20:30:00.000Z",
      "time": "21:30"
    },
    {
      "utc": "2026-02-03T20:45:00.000Z",
      "time": "21:45"
    },
    {
      "utc": "2026-02-03T21:00:00.000Z",
      "time": "22:00"
    },
    {
      "utc": "2026-02-03T21:15:00.000Z",
      "time": "22:15"
    },
    {
      "utc": "2026-02-03T21:30:00.000Z",
      "time": "22:30"
    },
    {
      "utc": "2026-02-03T21:45:00.000Z",
      "time": "22:45"
    },
    {
      "utc": "2026-02-03T22:00:00.000Z",
      "time": "23:00"
    },
    {
      "utc": "2026-02-03T22:15:00.000Z",
      "time": "23:15"
    },
    {
      "utc": "2026-02-03T22:30:00.000Z",
      "time": "23:30"
    },
    {
      "utc": "2026-02-03T22:45:00.000Z",
      "time": "23:45"
    }
  ],
  "raw": {
    "points": [
      {
        "utc": "2026-02-02T23:00:00.000Z",
        "time": "00:00",
        "eurMwh": 100.09,
        "sekKwh": 1.060303,
        "oreKwh": 106.03
      },
      {
        "utc": "2026-02-02T23:15:00.000Z",
        "time": "00:15",
        "eurMwh": 98.95,
        "sekKwh": 1.048227,
        "oreKwh": 104.823
      },
      {
        "utc": "2026-02-02T23:30:00.000Z",
        "time": "00:30",
        "eurMwh": 97.51,
        "sekKwh": 1.032972,
        "oreKwh": 103.297
      },
      {
        "utc": "2026-02-02T23:45:00.000Z",
        "time": "00:45",
        "eurMwh": 96.19,
        "sekKwh": 1.018989,
        "oreKwh": 101.899
      },
      {
        "utc": "2026-02-03T00:00:00.000Z",
        "time": "01:00",
        "eurMwh": 97.12,
        "sekKwh": 1.028841,
        "oreKwh": 102.884
      },
      {
        "utc": "2026-02-03T00:15:00.000Z",
        "time": "01:15",
        "eurMwh": 95.87,
        "sekKwh": 1.015599,
        "oreKwh": 101.56
      },
      {
        "utc": "2026-02-03T00:30:00.000Z",
        "time": "01:30",
        "eurMwh": 96.18,
        "sekKwh": 1.018883,
        "oreKwh": 101.888
      },
      {
        "utc": "2026-02-03T00:45:00.000Z",
        "time": "01:45",
        "eurMwh": 95.68,
        "sekKwh": 1.013586,
        "oreKwh": 101.359
      },
      {
        "utc": "2026-02-03T01:00:00.000Z",
        "time": "02:00",
        "eurMwh": 96.08,
        "sekKwh": 1.017823,
        "oreKwh": 101.782
      },
      {
        "utc": "2026-02-03T01:15:00.000Z",
        "time": "02:15",
        "eurMwh": 94.69,
        "sekKwh": 1.003099,
        "oreKwh": 100.31
      },
      {
        "utc": "2026-02-03T01:30:00.000Z",
        "time": "02:30",
        "eurMwh": 93.52,
        "sekKwh": 0.990704,
        "oreKwh": 99.07
      },
      {
        "utc": "2026-02-03T01:45:00.000Z",
        "time": "02:45",
        "eurMwh": 92.27,
        "sekKwh": 0.977462,
        "oreKwh": 97.746
      },
      {
        "utc": "2026-02-03T02:00:00.000Z",
        "time": "03:00",
        "eurMwh": 94.07,
        "sekKwh": 0.996531,
        "oreKwh": 99.653
      },
      {
        "utc": "2026-02-03T02:15:00.000Z",
        "time": "03:15",
        "eurMwh": 93.12,
        "sekKwh": 0.986467,
        "oreKwh": 98.647
      },
      {
        "utc": "2026-02-03T02:30:00.000Z",
        "time": "03:30",
        "eurMwh": 92.79,
        "sekKwh": 0.982971,
        "oreKwh": 98.297
      },
      {
        "utc": "2026-02-03T02:45:00.000Z",
        "time": "03:45",
        "eurMwh": 92.03,
        "sekKwh": 0.97492,
        "oreKwh": 97.492
      },
      {
        "utc": "2026-02-03T03:00:00.000Z",
        "time": "04:00",
        "eurMwh": 91.72,
        "sekKwh": 0.971636,
        "oreKwh": 97.164
      },
      {
        "utc": "2026-02-03T03:15:00.000Z",
        "time": "04:15",
        "eurMwh": 91.5,
        "sekKwh": 0.969305,
        "oreKwh": 96.931
      },
      {
        "utc": "2026-02-03T03:30:00.000Z",
        "time": "04:30",
        "eurMwh": 92.99,
        "sekKwh": 0.98509,
        "oreKwh": 98.509
      },
      {
        "utc": "2026-02-03T03:45:00.000Z",
        "time": "04:45",
        "eurMwh": 93.03,
        "sekKwh": 0.985513,
        "oreKwh": 98.551
      },
      {
        "utc": "2026-02-03T04:00:00.000Z",
        "time": "05:00",
        "eurMwh": 92.18,
        "sekKwh": 0.976509,
        "oreKwh": 97.651
      },
      {
        "utc": "2026-02-03T04:15:00.000Z",
        "time": "05:15",
        "eurMwh": 94.02,
        "sekKwh": 0.996001,
        "oreKwh": 99.6
      },
      {
        "utc": "2026-02-03T04:30:00.000Z",
        "time": "05:30",
        "eurMwh": 98.87,
        "sekKwh": 1.047379,
        "oreKwh": 104.738
      },
      {
        "utc": "2026-02-03T04:45:00.000Z",
        "time": "05:45",
        "eurMwh": 105.35,
        "sekKwh": 1.116025,
        "oreKwh": 111.603
      },
      {
        "utc": "2026-02-03T05:00:00.000Z",
        "time": "06:00",
        "eurMwh": 103.39,
        "sekKwh": 1.095262,
        "oreKwh": 109.526
      },
      {
        "utc": "2026-02-03T05:15:00.000Z",
        "time": "06:15",
        "eurMwh": 109.61,
        "sekKwh": 1.161154,
        "oreKwh": 116.115
      },
      {
        "utc": "2026-02-03T05:30:00.000Z",
        "time": "06:30",
        "eurMwh": 115.03,
        "sekKwh": 1.21857,
        "oreKwh": 121.857
      },
      {
        "utc": "2026-02-03T05:45:00.000Z",
        "time": "06:45",
        "eurMwh": 120.3,
        "sekKwh": 1.274398,
        "oreKwh": 127.44
      },
      {
        "utc": "2026-02-03T06:00:00.000Z",
        "time": "07:00",
        "eurMwh": 122.2,
        "sekKwh": 1.294526,
        "oreKwh": 129.453
      },
      {
        "utc": "2026-02-03T06:15:00.000Z",
        "time": "07:15",
        "eurMwh": 129,
        "sekKwh": 1.366562,
        "oreKwh": 136.656
      },
      {
        "utc": "2026-02-03T06:30:00.000Z",
        "time": "07:30",
        "eurMwh": 134.06,
        "sekKwh": 1.420165,
        "oreKwh": 142.016
      },
      {
        "utc": "2026-02-03T06:45:00.000Z",
        "time": "07:45",
        "eurMwh": 138.09,
        "sekKwh": 1.462856,
        "oreKwh": 146.286
      },
      {
        "utc": "2026-02-03T07:00:00.000Z",
        "time": "08:00",
        "eurMwh": 199.95,
        "sekKwh": 2.11817,
        "oreKwh": 211.817
      },
      {
        "utc": "2026-02-03T07:15:00.000Z",
        "time": "08:15",
        "eurMwh": 199.99,
        "sekKwh": 2.118594,
        "oreKwh": 211.859
      },
      {
        "utc": "2026-02-03T07:30:00.000Z",
        "time": "08:30",
        "eurMwh": 193.19,
        "sekKwh": 2.046558,
        "oreKwh": 204.656
      },
      {
        "utc": "2026-02-03T07:45:00.000Z",
        "time": "08:45",
        "eurMwh": 188.06,
        "sekKwh": 1.992214,
        "oreKwh": 199.221
      },
      {
        "utc": "2026-02-03T08:00:00.000Z",
        "time": "09:00",
        "eurMwh": 162.57,
        "sekKwh": 1.722185,
        "oreKwh": 172.219
      },
      {
        "utc": "2026-02-03T08:15:00.000Z",
        "time": "09:15",
        "eurMwh": 149.89,
        "sekKwh": 1.58786,
        "oreKwh": 158.786
      },
      {
        "utc": "2026-02-03T08:30:00.000Z",
        "time": "09:30",
        "eurMwh": 142.03,
        "sekKwh": 1.504595,
        "oreKwh": 150.459
      },
      {
        "utc": "2026-02-03T08:45:00.000Z",
        "time": "09:45",
        "eurMwh": 136.74,
        "sekKwh": 1.448555,
        "oreKwh": 144.856
      },
      {
        "utc": "2026-02-03T09:00:00.000Z",
        "time": "10:00",
        "eurMwh": 128.52,
        "sekKwh": 1.361477,
        "oreKwh": 136.148
      },
      {
        "utc": "2026-02-03T09:15:00.000Z",
        "time": "10:15",
        "eurMwh": 124.39,
        "sekKwh": 1.317725,
        "oreKwh": 131.773
      },
      {
        "utc": "2026-02-03T09:30:00.000Z",
        "time": "10:30",
        "eurMwh": 121.07,
        "sekKwh": 1.282555,
        "oreKwh": 128.256
      },
      {
        "utc": "2026-02-03T09:45:00.000Z",
        "time": "10:45",
        "eurMwh": 114.56,
        "sekKwh": 1.213591,
        "oreKwh": 121.359
      },
      {
        "utc": "2026-02-03T10:00:00.000Z",
        "time": "11:00",
        "eurMwh": 120.97,
        "sekKwh": 1.281496,
        "oreKwh": 128.15
      },
      {
        "utc": "2026-02-03T10:15:00.000Z",
        "time": "11:15",
        "eurMwh": 114.58,
        "sekKwh": 1.213803,
        "oreKwh": 121.38
      },
      {
        "utc": "2026-02-03T10:30:00.000Z",
        "time": "11:30",
        "eurMwh": 112.66,
        "sekKwh": 1.193464,
        "oreKwh": 119.346
      },
      {
        "utc": "2026-02-03T10:45:00.000Z",
        "time": "11:45",
        "eurMwh": 107.53,
        "sekKwh": 1.139119,
        "oreKwh": 113.912
      },
      {
        "utc": "2026-02-03T11:00:00.000Z",
        "time": "12:00",
        "eurMwh": 114.11,
        "sekKwh": 1.208824,
        "oreKwh": 120.882
      },
      {
        "utc": "2026-02-03T11:15:00.000Z",
        "time": "12:15",
        "eurMwh": 112.99,
        "sekKwh": 1.19696,
        "oreKwh": 119.696
      },
      {
        "utc": "2026-02-03T11:30:00.000Z",
        "time": "12:30",
        "eurMwh": 111.08,
        "sekKwh": 1.176726,
        "oreKwh": 117.673
      },
      {
        "utc": "2026-02-03T11:45:00.000Z",
        "time": "12:45",
        "eurMwh": 109.58,
        "sekKwh": 1.160836,
        "oreKwh": 116.084
      },
      {
        "utc": "2026-02-03T12:00:00.000Z",
        "time": "13:00",
        "eurMwh": 109.85,
        "sekKwh": 1.163696,
        "oreKwh": 116.37
      },
      {
        "utc": "2026-02-03T12:15:00.000Z",
        "time": "13:15",
        "eurMwh": 112.13,
        "sekKwh": 1.187849,
        "oreKwh": 118.785
      },
      {
        "utc": "2026-02-03T12:30:00.000Z",
        "time": "13:30",
        "eurMwh": 112.99,
        "sekKwh": 1.19696,
        "oreKwh": 119.696
      },
      {
        "utc": "2026-02-03T12:45:00.000Z",
        "time": "13:45",
        "eurMwh": 113,
        "sekKwh": 1.197066,
        "oreKwh": 119.707
      },
      {
        "utc": "2026-02-03T13:00:00.000Z",
        "time": "14:00",
        "eurMwh": 109.21,
        "sekKwh": 1.156916,
        "oreKwh": 115.692
      },
      {
        "utc": "2026-02-03T13:15:00.000Z",
        "time": "14:15",
        "eurMwh": 111.66,
        "sekKwh": 1.18287,
        "oreKwh": 118.287
      },
      {
        "utc": "2026-02-03T13:30:00.000Z",
        "time": "14:30",
        "eurMwh": 112.56,
        "sekKwh": 1.192404,
        "oreKwh": 119.24
      },
      {
        "utc": "2026-02-03T13:45:00.000Z",
        "time": "14:45",
        "eurMwh": 115.05,
        "sekKwh": 1.218782,
        "oreKwh": 121.878
      },
      {
        "utc": "2026-02-03T14:00:00.000Z",
        "time": "15:00",
        "eurMwh": 109.45,
        "sekKwh": 1.159459,
        "oreKwh": 115.946
      },
      {
        "utc": "2026-02-03T14:15:00.000Z",
        "time": "15:15",
        "eurMwh": 111.29,
        "sekKwh": 1.178951,
        "oreKwh": 117.895
      },
      {
        "utc": "2026-02-03T14:30:00.000Z",
        "time": "15:30",
        "eurMwh": 113.98,
        "sekKwh": 1.207447,
        "oreKwh": 120.745
      },
      {
        "utc": "2026-02-03T14:45:00.000Z",
        "time": "15:45",
        "eurMwh": 115.89,
        "sekKwh": 1.227681,
        "oreKwh": 122.768
      },
      {
        "utc": "2026-02-03T15:00:00.000Z",
        "time": "16:00",
        "eurMwh": 115.71,
        "sekKwh": 1.225774,
        "oreKwh": 122.577
      },
      {
        "utc": "2026-02-03T15:15:00.000Z",
        "time": "16:15",
        "eurMwh": 116.43,
        "sekKwh": 1.233401,
        "oreKwh": 123.34
      },
      {
        "utc": "2026-02-03T15:30:00.000Z",
        "time": "16:30",
        "eurMwh": 119.84,
        "sekKwh": 1.269525,
        "oreKwh": 126.953
      },
      {
        "utc": "2026-02-03T15:45:00.000Z",
        "time": "16:45",
        "eurMwh": 120.34,
        "sekKwh": 1.274822,
        "oreKwh": 127.482
      },
      {
        "utc": "2026-02-03T16:00:00.000Z",
        "time": "17:00",
        "eurMwh": 138.65,
        "sekKwh": 1.468789,
        "oreKwh": 146.879
      },
      {
        "utc": "2026-02-03T16:15:00.000Z",
        "time": "17:15",
        "eurMwh": 138.67,
        "sekKwh": 1.469001,
        "oreKwh": 146.9
      },
      {
        "utc": "2026-02-03T16:30:00.000Z",
        "time": "17:30",
        "eurMwh": 142.91,
        "sekKwh": 1.513917,
        "oreKwh": 151.392
      },
      {
        "utc": "2026-02-03T16:45:00.000Z",
        "time": "17:45",
        "eurMwh": 143.09,
        "sekKwh": 1.515824,
        "oreKwh": 151.582
      },
      {
        "utc": "2026-02-03T17:00:00.000Z",
        "time": "18:00",
        "eurMwh": 138.06,
        "sekKwh": 1.462539,
        "oreKwh": 146.254
      },
      {
        "utc": "2026-02-03T17:15:00.000Z",
        "time": "18:15",
        "eurMwh": 135.6,
        "sekKwh": 1.436479,
        "oreKwh": 143.648
      },
      {
        "utc": "2026-02-03T17:30:00.000Z",
        "time": "18:30",
        "eurMwh": 134.86,
        "sekKwh": 1.428639,
        "oreKwh": 142.864
      },
      {
        "utc": "2026-02-03T17:45:00.000Z",
        "time": "18:45",
        "eurMwh": 135.09,
        "sekKwh": 1.431076,
        "oreKwh": 143.108
      },
      {
        "utc": "2026-02-03T18:00:00.000Z",
        "time": "19:00",
        "eurMwh": 131.62,
        "sekKwh": 1.394316,
        "oreKwh": 139.432
      },
      {
        "utc": "2026-02-03T18:15:00.000Z",
        "time": "19:15",
        "eurMwh": 130.88,
        "sekKwh": 1.386477,
        "oreKwh": 138.648
      },
      {
        "utc": "2026-02-03T18:30:00.000Z",
        "time": "19:30",
        "eurMwh": 129.54,
        "sekKwh": 1.372282,
        "oreKwh": 137.228
      },
      {
        "utc": "2026-02-03T18:45:00.000Z",
        "time": "19:45",
        "eurMwh": 122.91,
        "sekKwh": 1.302047,
        "oreKwh": 130.205
      },
      {
        "utc": "2026-02-03T19:00:00.000Z",
        "time": "20:00",
        "eurMwh": 115.76,
        "sekKwh": 1.226304,
        "oreKwh": 122.63
      },
      {
        "utc": "2026-02-03T19:15:00.000Z",
        "time": "20:15",
        "eurMwh": 113.49,
        "sekKwh": 1.202256,
        "oreKwh": 120.226
      },
      {
        "utc": "2026-02-03T19:30:00.000Z",
        "time": "20:30",
        "eurMwh": 110.79,
        "sekKwh": 1.173654,
        "oreKwh": 117.365
      },
      {
        "utc": "2026-02-03T19:45:00.000Z",
        "time": "20:45",
        "eurMwh": 108.66,
        "sekKwh": 1.15109,
        "oreKwh": 115.109
      },
      {
        "utc": "2026-02-03T20:00:00.000Z",
        "time": "21:00",
        "eurMwh": 108.7,
        "sekKwh": 1.151513,
        "oreKwh": 115.151
      },
      {
        "utc": "2026-02-03T20:15:00.000Z",
        "time": "21:15",
        "eurMwh": 107.36,
        "sekKwh": 1.137318,
        "oreKwh": 113.732
      },
      {
        "utc": "2026-02-03T20:30:00.000Z",
        "time": "21:30",
        "eurMwh": 104.87,
        "sekKwh": 1.11094,
        "oreKwh": 111.094
      },
      {
        "utc": "2026-02-03T20:45:00.000Z",
        "time": "21:45",
        "eurMwh": 101.1,
        "sekKwh": 1.071003,
        "oreKwh": 107.1
      },
      {
        "utc": "2026-02-03T21:00:00.000Z",
        "time": "22:00",
        "eurMwh": 105.07,
        "sekKwh": 1.113059,
        "oreKwh": 111.306
      },
      {
        "utc": "2026-02-03T21:15:00.000Z",
        "time": "22:15",
        "eurMwh": 101.63,
        "sekKwh": 1.076617,
        "oreKwh": 107.662
      },
      {
        "utc": "2026-02-03T21:30:00.000Z",
        "time": "22:30",
        "eurMwh": 101.24,
        "sekKwh": 1.072486,
        "oreKwh": 107.249
      },
      {
        "utc": "2026-02-03T21:45:00.000Z",
        "time": "22:45",
        "eurMwh": 97.5,
        "sekKwh": 1.032866,
        "oreKwh": 103.287
      },
      {
        "utc": "2026-02-03T22:00:00.000Z",
        "time": "23:00",
        "eurMwh": 99.67,
        "sekKwh": 1.055854,
        "oreKwh": 105.585
      },
      {
        "utc": "2026-02-03T22:15:00.000Z",
        "time": "23:15",
        "eurMwh": 98.38,
        "sekKwh": 1.042189,
        "oreKwh": 104.219
      },
      {
        "utc": "2026-02-03T22:30:00.000Z",
        "time": "23:30",
        "eurMwh": 96.25,
        "sekKwh": 1.019624,
        "oreKwh": 101.962
      },
      {
        "utc": "2026-02-03T22:45:00.000Z",
        "time": "23:45",
        "eurMwh": 88.98,
        "sekKwh": 0.94261,
        "oreKwh": 94.261
      }
    ],
    "missingCount": 0
  },
  "extrapolated": {
    "method": "linear-internal-only",
    "points": [
      {
        "utc": "2026-02-02T23:00:00.000Z",
        "time": "00:00",
        "eurMwh": 100.09,
        "sekKwh": 1.060303,
        "oreKwh": 106.03
      },
      {
        "utc": "2026-02-02T23:15:00.000Z",
        "time": "00:15",
        "eurMwh": 98.95,
        "sekKwh": 1.048227,
        "oreKwh": 104.823
      },
      {
        "utc": "2026-02-02T23:30:00.000Z",
        "time": "00:30",
        "eurMwh": 97.51,
        "sekKwh": 1.032972,
        "oreKwh": 103.297
      },
      {
        "utc": "2026-02-02T23:45:00.000Z",
        "time": "00:45",
        "eurMwh": 96.19,
        "sekKwh": 1.018989,
        "oreKwh": 101.899
      },
      {
        "utc": "2026-02-03T00:00:00.000Z",
        "time": "01:00",
        "eurMwh": 97.12,
        "sekKwh": 1.028841,
        "oreKwh": 102.884
      },
      {
        "utc": "2026-02-03T00:15:00.000Z",
        "time": "01:15",
        "eurMwh": 95.87,
        "sekKwh": 1.015599,
        "oreKwh": 101.56
      },
      {
        "utc": "2026-02-03T00:30:00.000Z",
        "time": "01:30",
        "eurMwh": 96.18,
        "sekKwh": 1.018883,
        "oreKwh": 101.888
      },
      {
        "utc": "2026-02-03T00:45:00.000Z",
        "time": "01:45",
        "eurMwh": 95.68,
        "sekKwh": 1.013586,
        "oreKwh": 101.359
      },
      {
        "utc": "2026-02-03T01:00:00.000Z",
        "time": "02:00",
        "eurMwh": 96.08,
        "sekKwh": 1.017823,
        "oreKwh": 101.782
      },
      {
        "utc": "2026-02-03T01:15:00.000Z",
        "time": "02:15",
        "eurMwh": 94.69,
        "sekKwh": 1.003099,
        "oreKwh": 100.31
      },
      {
        "utc": "2026-02-03T01:30:00.000Z",
        "time": "02:30",
        "eurMwh": 93.52,
        "sekKwh": 0.990704,
        "oreKwh": 99.07
      },
      {
        "utc": "2026-02-03T01:45:00.000Z",
        "time": "02:45",
        "eurMwh": 92.27,
        "sekKwh": 0.977462,
        "oreKwh": 97.746
      },
      {
        "utc": "2026-02-03T02:00:00.000Z",
        "time": "03:00",
        "eurMwh": 94.07,
        "sekKwh": 0.996531,
        "oreKwh": 99.653
      },
      {
        "utc": "2026-02-03T02:15:00.000Z",
        "time": "03:15",
        "eurMwh": 93.12,
        "sekKwh": 0.986467,
        "oreKwh": 98.647
      },
      {
        "utc": "2026-02-03T02:30:00.000Z",
        "time": "03:30",
        "eurMwh": 92.79,
        "sekKwh": 0.982971,
        "oreKwh": 98.297
      },
      {
        "utc": "2026-02-03T02:45:00.000Z",
        "time": "03:45",
        "eurMwh": 92.03,
        "sekKwh": 0.97492,
        "oreKwh": 97.492
      },
      {
        "utc": "2026-02-03T03:00:00.000Z",
        "time": "04:00",
        "eurMwh": 91.72,
        "sekKwh": 0.971636,
        "oreKwh": 97.164
      },
      {
        "utc": "2026-02-03T03:15:00.000Z",
        "time": "04:15",
        "eurMwh": 91.5,
        "sekKwh": 0.969305,
        "oreKwh": 96.931
      },
      {
        "utc": "2026-02-03T03:30:00.000Z",
        "time": "04:30",
        "eurMwh": 92.99,
        "sekKwh": 0.98509,
        "oreKwh": 98.509
      },
      {
        "utc": "2026-02-03T03:45:00.000Z",
        "time": "04:45",
        "eurMwh": 93.03,
        "sekKwh": 0.985513,
        "oreKwh": 98.551
      },
      {
        "utc": "2026-02-03T04:00:00.000Z",
        "time": "05:00",
        "eurMwh": 92.18,
        "sekKwh": 0.976509,
        "oreKwh": 97.651
      },
      {
        "utc": "2026-02-03T04:15:00.000Z",
        "time": "05:15",
        "eurMwh": 94.02,
        "sekKwh": 0.996001,
        "oreKwh": 99.6
      },
      {
        "utc": "2026-02-03T04:30:00.000Z",
        "time": "05:30",
        "eurMwh": 98.87,
        "sekKwh": 1.047379,
        "oreKwh": 104.738
      },
      {
        "utc": "2026-02-03T04:45:00.000Z",
        "time": "05:45",
        "eurMwh": 105.35,
        "sekKwh": 1.116025,
        "oreKwh": 111.603
      },
      {
        "utc": "2026-02-03T05:00:00.000Z",
        "time": "06:00",
        "eurMwh": 103.39,
        "sekKwh": 1.095262,
        "oreKwh": 109.526
      },
      {
        "utc": "2026-02-03T05:15:00.000Z",
        "time": "06:15",
        "eurMwh": 109.61,
        "sekKwh": 1.161154,
        "oreKwh": 116.115
      },
      {
        "utc": "2026-02-03T05:30:00.000Z",
        "time": "06:30",
        "eurMwh": 115.03,
        "sekKwh": 1.21857,
        "oreKwh": 121.857
      },
      {
        "utc": "2026-02-03T05:45:00.000Z",
        "time": "06:45",
        "eurMwh": 120.3,
        "sekKwh": 1.274398,
        "oreKwh": 127.44
      },
      {
        "utc": "2026-02-03T06:00:00.000Z",
        "time": "07:00",
        "eurMwh": 122.2,
        "sekKwh": 1.294526,
        "oreKwh": 129.453
      },
      {
        "utc": "2026-02-03T06:15:00.000Z",
        "time": "07:15",
        "eurMwh": 129,
        "sekKwh": 1.366562,
        "oreKwh": 136.656
      },
      {
        "utc": "2026-02-03T06:30:00.000Z",
        "time": "07:30",
        "eurMwh": 134.06,
        "sekKwh": 1.420165,
        "oreKwh": 142.016
      },
      {
        "utc": "2026-02-03T06:45:00.000Z",
        "time": "07:45",
        "eurMwh": 138.09,
        "sekKwh": 1.462856,
        "oreKwh": 146.286
      },
      {
        "utc": "2026-02-03T07:00:00.000Z",
        "time": "08:00",
        "eurMwh": 199.95,
        "sekKwh": 2.11817,
        "oreKwh": 211.817
      },
      {
        "utc": "2026-02-03T07:15:00.000Z",
        "time": "08:15",
        "eurMwh": 199.99,
        "sekKwh": 2.118594,
        "oreKwh": 211.859
      },
      {
        "utc": "2026-02-03T07:30:00.000Z",
        "time": "08:30",
        "eurMwh": 193.19,
        "sekKwh": 2.046558,
        "oreKwh": 204.656
      },
      {
        "utc": "2026-02-03T07:45:00.000Z",
        "time": "08:45",
        "eurMwh": 188.06,
        "sekKwh": 1.992214,
        "oreKwh": 199.221
      },
      {
        "utc": "2026-02-03T08:00:00.000Z",
        "time": "09:00",
        "eurMwh": 162.57,
        "sekKwh": 1.722185,
        "oreKwh": 172.219
      },
      {
        "utc": "2026-02-03T08:15:00.000Z",
        "time": "09:15",
        "eurMwh": 149.89,
        "sekKwh": 1.58786,
        "oreKwh": 158.786
      },
      {
        "utc": "2026-02-03T08:30:00.000Z",
        "time": "09:30",
        "eurMwh": 142.03,
        "sekKwh": 1.504595,
        "oreKwh": 150.459
      },
      {
        "utc": "2026-02-03T08:45:00.000Z",
        "time": "09:45",
        "eurMwh": 136.74,
        "sekKwh": 1.448555,
        "oreKwh": 144.856
      },
      {
        "utc": "2026-02-03T09:00:00.000Z",
        "time": "10:00",
        "eurMwh": 128.52,
        "sekKwh": 1.361477,
        "oreKwh": 136.148
      },
      {
        "utc": "2026-02-03T09:15:00.000Z",
        "time": "10:15",
        "eurMwh": 124.39,
        "sekKwh": 1.317725,
        "oreKwh": 131.773
      },
      {
        "utc": "2026-02-03T09:30:00.000Z",
        "time": "10:30",
        "eurMwh": 121.07,
        "sekKwh": 1.282555,
        "oreKwh": 128.256
      },
      {
        "utc": "2026-02-03T09:45:00.000Z",
        "time": "10:45",
        "eurMwh": 114.56,
        "sekKwh": 1.213591,
        "oreKwh": 121.359
      },
      {
        "utc": "2026-02-03T10:00:00.000Z",
        "time": "11:00",
        "eurMwh": 120.97,
        "sekKwh": 1.281496,
        "oreKwh": 128.15
      },
      {
        "utc": "2026-02-03T10:15:00.000Z",
        "time": "11:15",
        "eurMwh": 114.58,
        "sekKwh": 1.213803,
        "oreKwh": 121.38
      },
      {
        "utc": "2026-02-03T10:30:00.000Z",
        "time": "11:30",
        "eurMwh": 112.66,
        "sekKwh": 1.193464,
        "oreKwh": 119.346
      },
      {
        "utc": "2026-02-03T10:45:00.000Z",
        "time": "11:45",
        "eurMwh": 107.53,
        "sekKwh": 1.139119,
        "oreKwh": 113.912
      },
      {
        "utc": "2026-02-03T11:00:00.000Z",
        "time": "12:00",
        "eurMwh": 114.11,
        "sekKwh": 1.208824,
        "oreKwh": 120.882
      },
      {
        "utc": "2026-02-03T11:15:00.000Z",
        "time": "12:15",
        "eurMwh": 112.99,
        "sekKwh": 1.19696,
        "oreKwh": 119.696
      },
      {
        "utc": "2026-02-03T11:30:00.000Z",
        "time": "12:30",
        "eurMwh": 111.08,
        "sekKwh": 1.176726,
        "oreKwh": 117.673
      },
      {
        "utc": "2026-02-03T11:45:00.000Z",
        "time": "12:45",
        "eurMwh": 109.58,
        "sekKwh": 1.160836,
        "oreKwh": 116.084
      },
      {
        "utc": "2026-02-03T12:00:00.000Z",
        "time": "13:00",
        "eurMwh": 109.85,
        "sekKwh": 1.163696,
        "oreKwh": 116.37
      },
      {
        "utc": "2026-02-03T12:15:00.000Z",
        "time": "13:15",
        "eurMwh": 112.13,
        "sekKwh": 1.187849,
        "oreKwh": 118.785
      },
      {
        "utc": "2026-02-03T12:30:00.000Z",
        "time": "13:30",
        "eurMwh": 112.99,
        "sekKwh": 1.19696,
        "oreKwh": 119.696
      },
      {
        "utc": "2026-02-03T12:45:00.000Z",
        "time": "13:45",
        "eurMwh": 113,
        "sekKwh": 1.197066,
        "oreKwh": 119.707
      },
      {
        "utc": "2026-02-03T13:00:00.000Z",
        "time": "14:00",
        "eurMwh": 109.21,
        "sekKwh": 1.156916,
        "oreKwh": 115.692
      },
      {
        "utc": "2026-02-03T13:15:00.000Z",
        "time": "14:15",
        "eurMwh": 111.66,
        "sekKwh": 1.18287,
        "oreKwh": 118.287
      },
      {
        "utc": "2026-02-03T13:30:00.000Z",
        "time": "14:30",
        "eurMwh": 112.56,
        "sekKwh": 1.192404,
        "oreKwh": 119.24
      },
      {
        "utc": "2026-02-03T13:45:00.000Z",
        "time": "14:45",
        "eurMwh": 115.05,
        "sekKwh": 1.218782,
        "oreKwh": 121.878
      },
      {
        "utc": "2026-02-03T14:00:00.000Z",
        "time": "15:00",
        "eurMwh": 109.45,
        "sekKwh": 1.159459,
        "oreKwh": 115.946
      },
      {
        "utc": "2026-02-03T14:15:00.000Z",
        "time": "15:15",
        "eurMwh": 111.29,
        "sekKwh": 1.178951,
        "oreKwh": 117.895
      },
      {
        "utc": "2026-02-03T14:30:00.000Z",
        "time": "15:30",
        "eurMwh": 113.98,
        "sekKwh": 1.207447,
        "oreKwh": 120.745
      },
      {
        "utc": "2026-02-03T14:45:00.000Z",
        "time": "15:45",
        "eurMwh": 115.89,
        "sekKwh": 1.227681,
        "oreKwh": 122.768
      },
      {
        "utc": "2026-02-03T15:00:00.000Z",
        "time": "16:00",
        "eurMwh": 115.71,
        "sekKwh": 1.225774,
        "oreKwh": 122.577
      },
      {
        "utc": "2026-02-03T15:15:00.000Z",
        "time": "16:15",
        "eurMwh": 116.43,
        "sekKwh": 1.233401,
        "oreKwh": 123.34
      },
      {
        "utc": "2026-02-03T15:30:00.000Z",
        "time": "16:30",
        "eurMwh": 119.84,
        "sekKwh": 1.269525,
        "oreKwh": 126.953
      },
      {
        "utc": "2026-02-03T15:45:00.000Z",
        "time": "16:45",
        "eurMwh": 120.34,
        "sekKwh": 1.274822,
        "oreKwh": 127.482
      },
      {
        "utc": "2026-02-03T16:00:00.000Z",
        "time": "17:00",
        "eurMwh": 138.65,
        "sekKwh": 1.468789,
        "oreKwh": 146.879
      },
      {
        "utc": "2026-02-03T16:15:00.000Z",
        "time": "17:15",
        "eurMwh": 138.67,
        "sekKwh": 1.469001,
        "oreKwh": 146.9
      },
      {
        "utc": "2026-02-03T16:30:00.000Z",
        "time": "17:30",
        "eurMwh": 142.91,
        "sekKwh": 1.513917,
        "oreKwh": 151.392
      },
      {
        "utc": "2026-02-03T16:45:00.000Z",
        "time": "17:45",
        "eurMwh": 143.09,
        "sekKwh": 1.515824,
        "oreKwh": 151.582
      },
      {
        "utc": "2026-02-03T17:00:00.000Z",
        "time": "18:00",
        "eurMwh": 138.06,
        "sekKwh": 1.462539,
        "oreKwh": 146.254
      },
      {
        "utc": "2026-02-03T17:15:00.000Z",
        "time": "18:15",
        "eurMwh": 135.6,
        "sekKwh": 1.436479,
        "oreKwh": 143.648
      },
      {
        "utc": "2026-02-03T17:30:00.000Z",
        "time": "18:30",
        "eurMwh": 134.86,
        "sekKwh": 1.428639,
        "oreKwh": 142.864
      },
      {
        "utc": "2026-02-03T17:45:00.000Z",
        "time": "18:45",
        "eurMwh": 135.09,
        "sekKwh": 1.431076,
        "oreKwh": 143.108
      },
      {
        "utc": "2026-02-03T18:00:00.000Z",
        "time": "19:00",
        "eurMwh": 131.62,
        "sekKwh": 1.394316,
        "oreKwh": 139.432
      },
      {
        "utc": "2026-02-03T18:15:00.000Z",
        "time": "19:15",
        "eurMwh": 130.88,
        "sekKwh": 1.386477,
        "oreKwh": 138.648
      },
      {
        "utc": "2026-02-03T18:30:00.000Z",
        "time": "19:30",
        "eurMwh": 129.54,
        "sekKwh": 1.372282,
        "oreKwh": 137.228
      },
      {
        "utc": "2026-02-03T18:45:00.000Z",
        "time": "19:45",
        "eurMwh": 122.91,
        "sekKwh": 1.302047,
        "oreKwh": 130.205
      },
      {
        "utc": "2026-02-03T19:00:00.000Z",
        "time": "20:00",
        "eurMwh": 115.76,
        "sekKwh": 1.226304,
        "oreKwh": 122.63
      },
      {
        "utc": "2026-02-03T19:15:00.000Z",
        "time": "20:15",
        "eurMwh": 113.49,
        "sekKwh": 1.202256,
        "oreKwh": 120.226
      },
      {
        "utc": "2026-02-03T19:30:00.000Z",
        "time": "20:30",
        "eurMwh": 110.79,
        "sekKwh": 1.173654,
        "oreKwh": 117.365
      },
      {
        "utc": "2026-02-03T19:45:00.000Z",
        "time": "20:45",
        "eurMwh": 108.66,
        "sekKwh": 1.15109,
        "oreKwh": 115.109
      },
      {
        "utc": "2026-02-03T20:00:00.000Z",
        "time": "21:00",
        "eurMwh": 108.7,
        "sekKwh": 1.151513,
        "oreKwh": 115.151
      },
      {
        "utc": "2026-02-03T20:15:00.000Z",
        "time": "21:15",
        "eurMwh": 107.36,
        "sekKwh": 1.137318,
        "oreKwh": 113.732
      },
      {
        "utc": "2026-02-03T20:30:00.000Z",
        "time": "21:30",
        "eurMwh": 104.87,
        "sekKwh": 1.11094,
        "oreKwh": 111.094
      },
      {
        "utc": "2026-02-03T20:45:00.000Z",
        "time": "21:45",
        "eurMwh": 101.1,
        "sekKwh": 1.071003,
        "oreKwh": 107.1
      },
      {
        "utc": "2026-02-03T21:00:00.000Z",
        "time": "22:00",
        "eurMwh": 105.07,
        "sekKwh": 1.113059,
        "oreKwh": 111.306
      },
      {
        "utc": "2026-02-03T21:15:00.000Z",
        "time": "22:15",
        "eurMwh": 101.63,
        "sekKwh": 1.076617,
        "oreKwh": 107.662
      },
      {
        "utc": "2026-02-03T21:30:00.000Z",
        "time": "22:30",
        "eurMwh": 101.24,
        "sekKwh": 1.072486,
        "oreKwh": 107.249
      },
      {
        "utc": "2026-02-03T21:45:00.000Z",
        "time": "22:45",
        "eurMwh": 97.5,
        "sekKwh": 1.032866,
        "oreKwh": 103.287
      },
      {
        "utc": "2026-02-03T22:00:00.000Z",
        "time": "23:00",
        "eurMwh": 99.67,
        "sekKwh": 1.055854,
        "oreKwh": 105.585
      },
      {
        "utc": "2026-02-03T22:15:00.000Z",
        "time": "23:15",
        "eurMwh": 98.38,
        "sekKwh": 1.042189,
        "oreKwh": 104.219
      },
      {
        "utc": "2026-02-03T22:30:00.000Z",
        "time": "23:30",
        "eurMwh": 96.25,
        "sekKwh": 1.019624,
        "oreKwh": 101.962
      },
      {
        "utc": "2026-02-03T22:45:00.000Z",
        "time": "23:45",
        "eurMwh": 88.98,
        "sekKwh": 0.94261,
        "oreKwh": 94.261
      }
    ],
    "filled": [
      false,
      false,
      false,
      false,
      false,
      false,
      false,
      false,
      false,
      false,
      false,
      false,
      false,
      false,
      false,
      false,
      false,
      false,
      false,
      false,
      false,
      false,
      false,
      false,
      false,
      false,
      false,
      false,
      false,
      false,
      false,
      false,
      false,
      false,
      false,
      false,
      false,
      false,
      false,
      false,
      false,
      false,
      false,
      false,
      false,
      false,
      false,
      false,
      false,
      false,
      false,
      false,
      false,
      false,
      false,
      false,
      false,
      false,
      false,
      false,
      false,
      false,
      false,
      false,
      false,
      false,
      false,
      false,
      false,
      false,
      false,
      false,
      false,
      false,
      false,
      false,
      false,
      false,
      false,
      false,
      false,
      false,
      false,
      false,
      false,
      false,
      false,
      false,
      false,
      false,
      false,
      false,
      false,
      false,
      false,
      false
    ],
    "stillNullCount": 0
  },
  "windows": {
    "raw": {
      "cheapest2h": {
        "startIndex": 13,
        "slots": 8,
        "startTime": "03:15",
        "endTime": "05:00",
        "avgOreKwh": 97.905
      },
      "cheapest4h": {
        "startIndex": 6,
        "slots": 16,
        "startTime": "01:30",
        "endTime": "05:15",
        "avgOreKwh": 99.041
      },
      "cheapest8h": {
        "startIndex": 0,
        "slots": 32,
        "startTime": "00:00",
        "endTime": "07:45",
        "avgOreKwh": 107.839
      }
    },
    "extrapolated": {
      "cheapest2h": {
        "startIndex": 13,
        "slots": 8,
        "startTime": "03:15",
        "endTime": "05:00",
        "avgOreKwh": 97.905
      },
      "cheapest4h": {
        "startIndex": 6,
        "slots": 16,
        "startTime": "01:30",
        "endTime": "05:15",
        "avgOreKwh": 99.041
      },
      "cheapest8h": {
        "startIndex": 0,
        "slots": 32,
        "startTime": "00:00",
        "endTime": "07:45",
        "avgOreKwh": 107.839
      }
    }
  }
}